pywebvtt/__init__.py
pywebvtt/errors.py
pywebvtt/scene.py
pywebvtt/timestamp.py
pywebvtt/webvtt.py
pywebvtt-0.2.0.dist-info/METADATA
pywebvtt-0.2.0.dist-info/WHEEL
pywebvtt-0.2.0.dist-info/RECORD
