Metadata-Version: 2.1
Name: pywebvtt
Version: 0.2.0
Summary: webvtt subtitle parser to traversable data struct
Author: AbhishekKr
Author-email: abhikumar163@gmail.com
Requires-Python: >=3.11,<4.0
Classifier: Programming Language :: Python :: 3
Classifier: Programming Language :: Python :: 3.11
